{
  "b": 37,
  "disableInputWhenNotFocused": true,
  "mangledName": "StartScreen",
  "name": "StartScreen",
  "r": 24,
  "standardSortMethod": true,
  "stopSoundsOnStartup": true,
  "title": "",
  "v": 20,
  "uiSettings": {
    "grid": false,
    "gridType": "rectangular",
    "gridWidth": 32,
    "gridHeight": 32,
    "gridOffsetX": 0,
    "gridOffsetY": 0,
    "gridColor": 10401023,
    "gridAlpha": 0.8,
    "snap": false,
    "zoomFactor": 1.2455500692651287,
    "windowMask": false
  },
  "objectsGroups": [],
  "variables": [],
  "instances": [
    {
      "angle": 0,
      "customSize": true,
      "height": 0,
      "layer": "",
      "name": "Intro_Flash",
      "persistentUuid": "7cb99578-de04-4d8e-a683-bca0ba58c74d",
      "width": 667,
      "x": 320,
      "y": 182,
      "zOrder": 1,
      "numberProperties": [],
      "stringProperties": [],
      "initialVariables": []
    },
    {
      "angle": 0,
      "customSize": false,
      "height": 0,
      "layer": "",
      "name": "StartButton",
      "persistentUuid": "d1274309-aeca-4701-b9af-77f26cf96385",
      "width": 0,
      "x": 287,
      "y": 236,
      "zOrder": 2,
      "numberProperties": [],
      "stringProperties": [],
      "initialVariables": []
    },
    {
      "angle": 0,
      "customSize": false,
      "height": 0,
      "layer": "",
      "name": "Title",
      "persistentUuid": "478afc43-a94e-4882-8da1-1cab633d1796",
      "width": 0,
      "x": 178,
      "y": 87,
      "zOrder": 3,
      "numberProperties": [],
      "stringProperties": [],
      "initialVariables": []
    },
    {
      "angle": 0,
      "customSize": false,
      "height": 0,
      "layer": "",
      "name": "coots_Intro",
      "persistentUuid": "0bdd4048-48f0-4feb-b5a7-06a67fd1c860",
      "width": 0,
      "x": 287,
      "y": 138,
      "zOrder": 4,
      "numberProperties": [],
      "stringProperties": [],
      "initialVariables": []
    },
    {
      "angle": 0,
      "customSize": false,
      "height": 0,
      "layer": "",
      "name": "Survive",
      "persistentUuid": "f38eef10-4b82-4d00-8729-e27373b21d6b",
      "width": 0,
      "x": 181,
      "y": 161,
      "zOrder": 5,
      "numberProperties": [],
      "stringProperties": [],
      "initialVariables": []
    }
  ],
  "objects": [
    {
      "assetStoreId": "",
      "name": "Intro_Flash",
      "tags": "",
      "type": "Sprite",
      "updateIfNotVisible": false,
      "variables": [],
      "effects": [],
      "behaviors": [
        {
          "name": "Tween",
          "type": "Tween::TweenBehavior"
        }
      ],
      "animations": [
        {
          "name": "Intro_Flash",
          "useMultipleDirections": false,
          "directions": [
            {
              "looping": false,
              "metadata": "{\"pskl\":{}}",
              "timeBetweenFrames": 0.08,
              "sprites": [
                {
                  "hasCustomCollisionMask": false,
                  "image": "NewSprite48",
                  "points": [],
                  "originPoint": {
                    "name": "origine",
                    "x": 8,
                    "y": 8
                  },
                  "centerPoint": {
                    "automatic": true,
                    "name": "centre",
                    "x": 0,
                    "y": 0
                  },
                  "customCollisionMask": []
                }
              ]
            }
          ]
        }
      ]
    },
    {
      "assetStoreId": "f0c3d7ae6099e3b9b8beed4e30b555107550b4fb2a5879e984a014b1e06865bf",
      "name": "StartButton",
      "tags": "",
      "type": "PanelSpriteButton::PanelSpriteButton",
      "variables": [],
      "effects": [],
      "behaviors": [
        {
          "name": "Tween",
          "type": "Tween::TweenBehavior"
        }
      ],
      "content": {
        "LeftPadding": 0,
        "RightPadding": 0,
        "PressedLabelOffsetY": 4,
        "BottomPadding": 0,
        "TopPadding": 0,
        "HoveredFadeOutDuration": 0
      },
      "childrenContent": {
        "Hovered": {
          "bottomMargin": 0,
          "height": 20,
          "leftMargin": 0,
          "rightMargin": 0,
          "texture": "StartButton3.png2",
          "tiled": false,
          "topMargin": 0,
          "width": 64
        },
        "Idle": {
          "bottomMargin": 0,
          "height": 20,
          "leftMargin": 0,
          "rightMargin": 0,
          "texture": "StartButton2.png",
          "tiled": false,
          "topMargin": 0,
          "width": 64
        },
        "Label": {
          "bold": false,
          "italic": false,
          "smoothed": true,
          "underlined": false,
          "string": "",
          "font": "",
          "textAlignment": "center",
          "characterSize": 0,
          "color": {
            "b": 255,
            "g": 255,
            "r": 255
          }
        },
        "Pressed": {
          "bottomMargin": 0,
          "height": 20,
          "leftMargin": 0,
          "rightMargin": 0,
          "texture": "StartButton4.png2",
          "tiled": false,
          "topMargin": 0,
          "width": 64
        }
      }
    },
    {
      "assetStoreId": "",
      "name": "Title",
      "tags": "",
      "type": "Sprite",
      "updateIfNotVisible": false,
      "variables": [],
      "effects": [],
      "behaviors": [
        {
          "name": "Tween",
          "type": "Tween::TweenBehavior"
        }
      ],
      "animations": [
        {
          "name": "",
          "useMultipleDirections": false,
          "directions": [
            {
              "looping": false,
              "timeBetweenFrames": 0.08,
              "sprites": [
                {
                  "hasCustomCollisionMask": false,
                  "image": "Title.png",
                  "points": [],
                  "originPoint": {
                    "name": "origine",
                    "x": 0,
                    "y": 0
                  },
                  "centerPoint": {
                    "automatic": true,
                    "name": "centre",
                    "x": 0,
                    "y": 0
                  },
                  "customCollisionMask": []
                }
              ]
            }
          ]
        }
      ]
    },
    {
      "assetStoreId": "",
      "name": "coots_Intro",
      "tags": "",
      "type": "Sprite",
      "updateIfNotVisible": false,
      "variables": [],
      "effects": [],
      "behaviors": [
        {
          "name": "Tween",
          "type": "Tween::TweenBehavior"
        }
      ],
      "animations": [
        {
          "name": "NewSprite",
          "useMultipleDirections": false,
          "directions": [
            {
              "looping": true,
              "metadata": "{\"pskl\":{}}",
              "timeBetweenFrames": 0.5,
              "sprites": [
                {
                  "hasCustomCollisionMask": false,
                  "image": "NewSprite",
                  "points": [],
                  "originPoint": {
                    "name": "origine",
                    "x": 0,
                    "y": 0
                  },
                  "centerPoint": {
                    "automatic": true,
                    "name": "centre",
                    "x": 0,
                    "y": 0
                  },
                  "customCollisionMask": []
                },
                {
                  "hasCustomCollisionMask": false,
                  "image": "NewSprite49",
                  "points": [],
                  "originPoint": {
                    "name": "origine",
                    "x": 0,
                    "y": 0
                  },
                  "centerPoint": {
                    "automatic": true,
                    "name": "centre",
                    "x": 0,
                    "y": 0
                  },
                  "customCollisionMask": []
                }
              ]
            }
          ]
        }
      ]
    },
    {
      "assetStoreId": "",
      "name": "Survive",
      "tags": "",
      "type": "Sprite",
      "updateIfNotVisible": false,
      "variables": [],
      "effects": [],
      "behaviors": [],
      "animations": [
        {
          "name": "",
          "useMultipleDirections": false,
          "directions": [
            {
              "looping": false,
              "timeBetweenFrames": 0.08,
              "sprites": [
                {
                  "hasCustomCollisionMask": false,
                  "image": "Survive.png",
                  "points": [],
                  "originPoint": {
                    "name": "origine",
                    "x": 0,
                    "y": 0
                  },
                  "centerPoint": {
                    "automatic": true,
                    "name": "centre",
                    "x": 0,
                    "y": 0
                  },
                  "customCollisionMask": []
                }
              ]
            }
          ]
        }
      ]
    }
  ],
  "events": [
    {
      "type": "BuiltinCommonInstructions::Standard",
      "conditions": [
        {
          "type": {
            "value": "DepartScene"
          },
          "parameters": [
            ""
          ]
        }
      ],
      "actions": [
        {
          "type": {
            "value": "SetWindowSize"
          },
          "parameters": [
            "",
            "1280",
            "720",
            ""
          ]
        },
        {
          "type": {
            "value": "CenterWindow"
          },
          "parameters": [
            ""
          ]
        },
        {
          "type": {
            "value": "SetFullScreen"
          },
          "parameters": [
            "",
            "yes",
            ""
          ]
        },
        {
          "type": {
            "value": "ZoomCamera"
          },
          "parameters": [
            "",
            "2",
            "",
            ""
          ]
        },
        {
          "type": {
            "value": "Cache"
          },
          "parameters": [
            "Survive"
          ]
        },
        {
          "type": {
            "value": "Cache"
          },
          "parameters": [
            "StartButton"
          ]
        },
        {
          "type": {
            "value": "Cache"
          },
          "parameters": [
            "Title"
          ]
        },
        {
          "type": {
            "value": "Cache"
          },
          "parameters": [
            "coots_Intro"
          ]
        },
        {
          "type": {
            "value": "Wait"
          },
          "parameters": [
            "1"
          ]
        },
        {
          "type": {
            "value": "Tween::AddObjectHeightTween"
          },
          "parameters": [
            "Intro_Flash",
            "Tween",
            "\"FlashIn\"",
            "16",
            "\"easeOutQuad\"",
            "250",
            ""
          ]
        }
      ]
    },
    {
      "type": "BuiltinCommonInstructions::Standard",
      "conditions": [
        {
          "type": {
            "value": "Tween::HasFinished"
          },
          "parameters": [
            "Intro_Flash",
            "Tween",
            "\"FlashIn\""
          ]
        }
      ],
      "actions": [
        {
          "type": {
            "value": "Tween::AddObjectHeightTween"
          },
          "parameters": [
            "Intro_Flash",
            "Tween",
            "\"FlashIn_Big\"",
            "360",
            "\"linear\"",
            "100",
            ""
          ]
        }
      ]
    },
    {
      "type": "BuiltinCommonInstructions::Standard",
      "conditions": [
        {
          "type": {
            "value": "Tween::HasFinished"
          },
          "parameters": [
            "Intro_Flash",
            "Tween",
            "\"FlashIn_Big\""
          ]
        }
      ],
      "actions": [
        {
          "type": {
            "value": "Tween::RemoveTween"
          },
          "parameters": [
            "Intro_Flash",
            "Tween",
            "\"FlashIn\""
          ]
        }
      ]
    },
    {
      "type": "BuiltinCommonInstructions::Standard",
      "conditions": [
        {
          "type": {
            "value": "Tween::IsPlaying"
          },
          "parameters": [
            "Intro_Flash",
            "Tween",
            "\"FlashIn_Big\""
          ]
        }
      ],
      "actions": [
        {
          "type": {
            "value": "Tween::AddObjectOpacityTween"
          },
          "parameters": [
            "Intro_Flash",
            "Tween",
            "\"FadeWhite\"",
            "0",
            "\"linear\"",
            "500",
            "no"
          ]
        }
      ]
    },
    {
      "type": "BuiltinCommonInstructions::Standard",
      "conditions": [
        {
          "type": {
            "value": "Tween::Exists"
          },
          "parameters": [
            "Intro_Flash",
            "Tween",
            "\"FadeWhite\""
          ]
        },
        {
          "type": {
            "value": "BuiltinCommonInstructions::Once"
          },
          "parameters": []
        }
      ],
      "actions": [
        {
          "type": {
            "value": "Wait"
          },
          "parameters": [
            "1"
          ]
        },
        {
          "type": {
            "value": "Montre"
          },
          "parameters": [
            "Title",
            ""
          ]
        },
        {
          "type": {
            "value": "Wait"
          },
          "parameters": [
            "1"
          ]
        },
        {
          "type": {
            "value": "Montre"
          },
          "parameters": [
            "coots_Intro",
            ""
          ]
        },
        {
          "type": {
            "value": "PlaySoundCanal"
          },
          "parameters": [
            "",
            "Coots_Intro.mp3",
            "1",
            "yes",
            "80",
            ""
          ]
        },
        {
          "type": {
            "value": "Wait"
          },
          "parameters": [
            "1"
          ]
        },
        {
          "type": {
            "value": "Montre"
          },
          "parameters": [
            "StartButton",
            ""
          ]
        }
      ]
    },
    {
      "type": "BuiltinCommonInstructions::Standard",
      "conditions": [
        {
          "type": {
            "value": "PanelSpriteButton::PanelSpriteButton::IsHovered"
          },
          "parameters": [
            "StartButton",
            ""
          ]
        }
      ],
      "actions": [],
      "events": [
        {
          "type": "BuiltinCommonInstructions::Standard",
          "conditions": [
            {
              "type": {
                "value": "BuiltinCommonInstructions::Once"
              },
              "parameters": []
            }
          ],
          "actions": [
            {
              "type": {
                "value": "PlaySound"
              },
              "parameters": [
                "",
                "Blip",
                "",
                "30",
                ""
              ]
            }
          ]
        }
      ]
    },
    {
      "type": "BuiltinCommonInstructions::Standard",
      "conditions": [
        {
          "type": {
            "value": "PanelSpriteButton::PanelSpriteButton::IsPressed"
          },
          "parameters": [
            "StartButton",
            ""
          ]
        }
      ],
      "actions": [
        {
          "type": {
            "value": "Tween::AddObjectOpacityTween"
          },
          "parameters": [
            "StartButton",
            "Tween",
            "\"FadeOut_Button\"",
            "0",
            "\"linear\"",
            "1000",
            "no"
          ]
        },
        {
          "type": {
            "value": "Tween::AddObjectOpacityTween"
          },
          "parameters": [
            "coots_Intro",
            "Tween",
            "\"FadeOut_Coots\"",
            "0",
            "\"linear\"",
            "1000",
            "no"
          ]
        },
        {
          "type": {
            "value": "Tween::AddObjectOpacityTween"
          },
          "parameters": [
            "Title",
            "Tween",
            "\"FadeOut_Title\"",
            "0",
            "\"linear\"",
            "1000",
            "no"
          ]
        },
        {
          "type": {
            "value": "FadeSoundVolume"
          },
          "parameters": [
            "",
            "1",
            "0",
            "1"
          ]
        },
        {
          "type": {
            "value": "PlaySound"
          },
          "parameters": [
            "",
            "Levelup.mp3",
            "",
            "30",
            ""
          ]
        }
      ]
    },
    {
      "type": "BuiltinCommonInstructions::Standard",
      "conditions": [
        {
          "type": {
            "value": "Opacity"
          },
          "parameters": [
            "coots_Intro",
            "=",
            "0"
          ]
        },
        {
          "type": {
            "value": "BuiltinCommonInstructions::Once"
          },
          "parameters": []
        }
      ],
      "actions": [
        {
          "type": {
            "value": "Montre"
          },
          "parameters": [
            "Survive",
            ""
          ]
        },
        {
          "type": {
            "value": "ResetTimer"
          },
          "parameters": [
            "",
            "\"Begin\""
          ]
        }
      ]
    },
    {
      "type": "BuiltinCommonInstructions::Standard",
      "conditions": [
        {
          "type": {
            "value": "CompareTimer"
          },
          "parameters": [
            "",
            "\"Begin\"",
            ">",
            "2"
          ]
        }
      ],
      "actions": [
        {
          "type": {
            "value": "RemoveTimer"
          },
          "parameters": [
            "",
            "\"Begin\""
          ]
        },
        {
          "type": {
            "value": "Scene"
          },
          "parameters": [
            "",
            "\"Battlefield\"",
            ""
          ]
        }
      ]
    }
  ],
  "layers": [
    {
      "ambientLightColorB": 10980712,
      "ambientLightColorG": 150995054,
      "ambientLightColorR": 1869182049,
      "followBaseLayerCamera": false,
      "isLightingLayer": false,
      "name": "",
      "visibility": true,
      "cameras": [
        {
          "defaultSize": true,
          "defaultViewport": true,
          "height": 0,
          "viewportBottom": 1,
          "viewportLeft": 0,
          "viewportRight": 1,
          "viewportTop": 0,
          "width": 0
        }
      ],
      "effects": []
    }
  ],
  "behaviorsSharedData": [
    {
      "name": "Tween",
      "type": "Tween::TweenBehavior"
    }
  ]
}